{
    "data": [
        {
            "created_at": "2013-07-20T06:36:06.000Z",
            "description": "\u201cMen are still good. We fight, we kill, we betray one another, but we can rebuild. We can do better. We will. We have to.\u201d",
            "id": "1607591160",
            "location": "Brasil",
            "name": "Luke",
            "public_metrics": {
                "followers_count": 1900,
                "following_count": 3882,
                "listed_count": 0,
                "tweet_count": 18707
            },
            "username": "LukeLightwood97"
        }
    ]
}