{
    "data": [
        {
            "created_at": "2009-10-01T02:24:43.000Z",
            "description": "Proud Trump Follower, Thank God everyday for bringing us Donald Trump! America First",
            "id": "78777205",
            "location": "Colorado Springs, CO",
            "name": "bichonlover",
            "public_metrics": {
                "followers_count": 973,
                "following_count": 1591,
                "listed_count": 0,
                "tweet_count": 122762
            },
            "username": "iluvshues"
        }
    ]
}