{
    "data": [
        {
            "created_at": "2009-03-20T22:03:27.000Z",
            "description": "Economics/politics for purpose of world peace and prosperity.\nLove animals & beauty of Earth and Cosmos",
            "id": "25585451",
            "location": "Colorado, USA",
            "name": "Linda",
            "public_metrics": {
                "followers_count": 425,
                "following_count": 201,
                "listed_count": 4,
                "tweet_count": 30983
            },
            "username": "lgfocus"
        }
    ]
}