{
    "data": [
        {
            "created_at": "2012-08-21T16:35:11.000Z",
            "description": "#IStandWithDonbass\n#GolanIsSyria\n#KosovoIsSerbia\n#IStandWithRussia",
            "entities": {
                "description": {
                    "hashtags": [
                        {
                            "end": 18,
                            "start": 0,
                            "tag": "IStandWithDonbass"
                        },
                        {
                            "end": 32,
                            "start": 19,
                            "tag": "GolanIsSyria"
                        },
                        {
                            "end": 48,
                            "start": 33,
                            "tag": "KosovoIsSerbia"
                        },
                        {
                            "end": 66,
                            "start": 49,
                            "tag": "IStandWithRussia"
                        }
                    ]
                },
                "url": {
                    "urls": [
                        {
                            "display_url": "t.me/EurasianChoice",
                            "end": 23,
                            "expanded_url": "https://t.me/EurasianChoice",
                            "start": 0,
                            "url": "https://t.co/p1cCzqhwmh"
                        }
                    ]
                }
            },
            "id": "771820890",
            "location": "Gillingham,UK",
            "name": "peter pobjecky - #FreeAssange",
            "public_metrics": {
                "followers_count": 5164,
                "following_count": 2344,
                "listed_count": 125,
                "tweet_count": 494284
            },
            "username": "peterpobjecky"
        }
    ]
}