{
    "data": [
        {
            "created_at": "2019-05-24T17:08:17.000Z",
            "description": "This Is The Official Twitter Page Of Midge Mathis.  I am a human and civil rights activist.",
            "id": "1131970183218716672",
            "location": "Arizona",
            "name": "Midge Mathis",
            "public_metrics": {
                "followers_count": 4920,
                "following_count": 5260,
                "listed_count": 14,
                "tweet_count": 46275
            },
            "username": "JusticeTargeted"
        }
    ]
}