{
    "data": [
        {
            "created_at": "2011-09-15T12:42:50.000Z",
            "description": "Christian Patriot, Ret. AF Vet-Back the Blue (father was a slain Deputy)-Microbiologist-MPH (Env Hlth):Fauxci damaged trust in PH-LSU Tiger on Sat-Saint on Sun",
            "id": "373938490",
            "location": "Pineville, Louisiana",
            "name": "CHRISTIAN AF Veteran",
            "public_metrics": {
                "followers_count": 1321,
                "following_count": 2237,
                "listed_count": 51,
                "tweet_count": 122542
            },
            "username": "sapmcdowell"
        }
    ]
}