{
    "data": [
        {
            "created_at": "2016-11-28T05:26:02.000Z",
            "description": "100%  patriot. mom. grandma.\nlove my country.\nlove America's true President\nPro Life\nPro Trump\ndown with commies, marxists, libs and socialist demonicrats",
            "id": "803107663089467392",
            "location": "Illinois",
            "name": "ElectricAngel69",
            "public_metrics": {
                "followers_count": 426,
                "following_count": 883,
                "listed_count": 1,
                "tweet_count": 37765
            },
            "username": "ElectricAngel69"
        }
    ]
}